README.txt
setup.cfg
setup.py
docs/HISTORY.txt
docs/INSTALL.txt
docs/LICENSE.GPL
docs/LICENSE.txt
redturtle/__init__.py
redturtle.portlet.lightreviewlist.egg-info/PKG-INFO
redturtle.portlet.lightreviewlist.egg-info/SOURCES.txt
redturtle.portlet.lightreviewlist.egg-info/dependency_links.txt
redturtle.portlet.lightreviewlist.egg-info/entry_points.txt
redturtle.portlet.lightreviewlist.egg-info/namespace_packages.txt
redturtle.portlet.lightreviewlist.egg-info/not-zip-safe
redturtle.portlet.lightreviewlist.egg-info/requires.txt
redturtle.portlet.lightreviewlist.egg-info/top_level.txt
redturtle/portlet/__init__.py
redturtle/portlet/lightreviewlist/__init__.py
redturtle/portlet/lightreviewlist/configure.zcml
redturtle/portlet/lightreviewlist/lightreviewlist.pt
redturtle/portlet/lightreviewlist/lightreviewlist.py
redturtle/portlet/lightreviewlist/rebuild_i18n.sh
redturtle/portlet/lightreviewlist/locales/redturtle.portlet.lightreviewlist-manual.pot
redturtle/portlet/lightreviewlist/locales/redturtle.portlet.lightreviewlist.pot
redturtle/portlet/lightreviewlist/locales/it/LC_MESSAGES/redturtle.portlet.lightreviewlist.mo
redturtle/portlet/lightreviewlist/locales/it/LC_MESSAGES/redturtle.portlet.lightreviewlist.po
redturtle/portlet/lightreviewlist/profiles/default/metadata.xml
redturtle/portlet/lightreviewlist/profiles/default/portlets.xml
redturtle/portlet/lightreviewlist/tests/__init__.py
redturtle/portlet/lightreviewlist/tests/base.py
redturtle/portlet/lightreviewlist/tests/test_portlet.py