Metadata-Version: 1.0
Name: redturtle.portlet.lightreviewlist
Version: 0.1.0
Summary: A light version of the Plone review_list portlet
Home-page: http://svn.plone.org/svn/collective/redturtle.portlet.lightreviewlist
Author: RedTurtle Technology
Author-email: sviluppoplone@redturtle.net
License: GPL
Keywords: plone portlet review_list
Platform: UNKNOWN
Classifier: Framework :: Plone
Classifier: Programming Language :: Python
Classifier: Topic :: Software Development :: Libraries :: Python Modules
